step_rest_client/__init__.py
step_rest_client/api_client.py
step_rest_client/api_response.py
step_rest_client/configuration.py
step_rest_client/exceptions.py
step_rest_client/py.typed
step_rest_client/rest.py
step_rest_client/api/__init__.py
step_rest_client/api/assets_api.py
step_rest_client/api/attributes_api.py
step_rest_client/api/background_process_types_api.py
step_rest_client/api/background_processes_api.py
step_rest_client/api/classifications_api.py
step_rest_client/api/data_container_types_api.py
step_rest_client/api/data_type_groups_api.py
step_rest_client/api/entities_api.py
step_rest_client/api/event_processors_api.py
step_rest_client/api/export_api.py
step_rest_client/api/gateway_integration_endpoints_api.py
step_rest_client/api/import_api.py
step_rest_client/api/inbound_integration_endpoints_api.py
step_rest_client/api/lists_of_values_api.py
step_rest_client/api/object_types_api.py
step_rest_client/api/outbound_integration_endpoints_api.py
step_rest_client/api/products_api.py
step_rest_client/api/reference_types_api.py
step_rest_client/api/reporting_api.py
step_rest_client/api/units_api.py
step_rest_client/api/workflow_tasks_api.py
step_rest_client/api/workflows_api.py
step_rest_client/models/__init__.py
step_rest_client/models/amount.py
step_rest_client/models/and_condition.py
step_rest_client/models/approval_response.py
step_rest_client/models/approval_status.py
step_rest_client/models/asset.py
step_rest_client/models/attribute.py
step_rest_client/models/attribute_link.py
step_rest_client/models/background_process.py
step_rest_client/models/background_process_attachment_metadata.py
step_rest_client/models/background_process_identification.py
step_rest_client/models/background_process_type.py
step_rest_client/models/classification.py
step_rest_client/models/condition.py
step_rest_client/models/data_container.py
step_rest_client/models/data_container_entry.py
step_rest_client/models/data_container_object_condition.py
step_rest_client-1.0.0.dist-info/METADATA
step_rest_client-1.0.0.dist-info/WHEEL
step_rest_client-1.0.0.dist-info/top_level.txt
step_rest_client-1.0.0.dist-info/RECORD
